{
  "team1": {
    "teamId": "FRA",
    "formation": "4-2-3-1",
    "startingXI": [
      {
        "no": 16,
        "pos": "GK"
      },
      {
        "no": 3,
        "pos": "DF"
      },
      {
        "no": 4,
        "pos": "DF"
      },
      {
        "no": 5,
        "pos": "DF"
      },
      {
        "no": 17,
        "pos": "DF"
      },
      {
        "no": 8,
        "pos": "MF"
      },
      {
        "no": 14,
        "pos": "MF"
      },
      {
        "no": 7,
        "pos": "FW"
      },
      {
        "no": 10,
        "pos": "FW",
        "captain": true
      },
      {
        "no": 11,
        "pos": "FW"
      },
      {
        "no": 12,
        "pos": "FW"
      }
    ],
    "substitutes": [
      {
        "no": 1
      },
      {
        "no": 23
      },
      {
        "no": 2
      },
      {
        "no": 15
      },
      {
        "no": 19
      },
      {
        "no": 21
      },
      {
        "no": 26
      },
      {
        "no": 6
      },
      {
        "no": 13
      },
      {
        "no": 18
      },
      {
        "no": 24
      },
      {
        "no": 25
      },
      {
        "no": 9
      },
      {
        "no": 20
      },
      {
        "no": 22
      }
    ],
    "coach": "Didier Deschamps"
  },
  "team2": {
    "teamId": "SWE",
    "formation": "4-4-2",
    "startingXI": [
      {
        "no": 1,
        "pos": "GK"
      },
      {
        "no": 2,
        "pos": "DF"
      },
      {
        "no": 3,
        "pos": "DF",
        "captain": true
      },
      {
        "no": 5,
        "pos": "DF"
      },
      {
        "no": 8,
        "pos": "DF"
      },
      {
        "no": 24,
        "pos": "DF"
      },
      {
        "no": 7,
        "pos": "MF"
      },
      {
        "no": 18,
        "pos": "MF"
      },
      {
        "no": 9,
        "pos": "FW"
      },
      {
        "no": 11,
        "pos": "FW"
      },
      {
        "no": 17,
        "pos": "FW"
      }
    ],
    "substitutes": [
      {
        "no": 12
      },
      {
        "no": 23
      },
      {
        "no": 6
      },
      {
        "no": 14
      },
      {
        "no": 15
      },
      {
        "no": 20
      },
      {
        "no": 21
      },
      {
        "no": 10
      },
      {
        "no": 13
      },
      {
        "no": 16
      },
      {
        "no": 19
      },
      {
        "no": 22
      },
      {
        "no": 25
      },
      {
        "no": 26
      }
    ],
    "coach": "Graham POTTER"
  },
  "substitutions": [
    {
      "minute": 65,
      "teamId": "SWE",
      "off": {
        "no": 24,
        "name": "Elliot STROUD"
      },
      "on": {
        "no": 26,
        "name": "Taha ALI"
      }
    },
    {
      "minute": 65,
      "teamId": "SWE",
      "off": {
        "no": 7,
        "name": "Lucas BERGVALL"
      },
      "on": {
        "no": 22,
        "name": "Besfort ZENELI"
      }
    },
    {
      "minute": 75,
      "teamId": "FRA",
      "off": {
        "no": 7,
        "name": "Ousmane DEMBELE"
      },
      "on": {
        "no": 20,
        "name": "Desire DOUE"
      }
    },
    {
      "minute": 75,
      "teamId": "FRA",
      "off": {
        "no": 5,
        "name": "Jules KOUNDE"
      },
      "on": {
        "no": 2,
        "name": "Malo GUSTO"
      }
    },
    {
      "minute": 78,
      "teamId": "FRA",
      "off": {
        "no": 3,
        "name": "Lucas DIGNE"
      },
      "on": {
        "no": 19,
        "name": "Theo HERNANDEZ"
      }
    },
    {
      "minute": 82,
      "teamId": "SWE",
      "off": {
        "no": 8,
        "name": "Daniel SVENSSON"
      },
      "on": {
        "no": 19,
        "name": "Mattias SVANBERG"
      }
    },
    {
      "minute": 82,
      "teamId": "SWE",
      "off": {
        "no": 18,
        "name": "Yasin AYARI"
      },
      "on": {
        "no": 10,
        "name": "Benjamin NYGREN"
      }
    },
    {
      "minute": 85,
      "teamId": "FRA",
      "off": {
        "no": 10,
        "name": "Kylian MBAPPE"
      },
      "on": {
        "no": 22,
        "name": "Jean-Philippe MATETA"
      }
    },
    {
      "minute": 85,
      "teamId": "FRA",
      "off": {
        "no": 11,
        "name": "Michael OLISE"
      },
      "on": {
        "no": 24,
        "name": "Rayan CHERKI"
      }
    },
    {
      "minute": 89,
      "teamId": "SWE",
      "off": {
        "no": 9,
        "name": "Alexander ISAK"
      },
      "on": {
        "no": 25,
        "name": "Gustaf NILSSON"
      }
    }
  ],
  "cards": []
}